[{"id":"finding-AEtNRRvz","date":"2018-10-28T20:50:05.173Z","mediaFilename":"finding-AEtNRRvz.png","caption":"Something Strange + <a href=\"PIA19041\">Rare Glance at Dark Side of Comet 67P/Churyumov-Gerasimenko</a>.","altText":"Something Strange + Rare Glance at Dark Side of Comet 67P/Churyumov-Gerasimenko. PIA19041","postedToGit":true,"htmlFragment":"<li class=\"pane\">\n  <div class=\"time-stamp entry-meta\">\n    <a href=\"finding-AEtNRRvz.html\">\n      <time datetime=\"2018-10-28T20:50:05.173Z\">2018-10-28 16:50:05</time>\n    </a>\n  </div><img src=\"media/finding-AEtNRRvz.png\" alt=\"Something Strange + Rare Glance at Dark Side of Comet 67P/Churyumov-Gerasimenko. PIA19041\"></video><div class=\"media-caption entry-meta\">Something Strange + <a href=\"PIA19041\">Rare Glance at Dark Side of Comet 67P/Churyumov-Gerasimenko</a>.</div></li>","postedSingleVideoPage":true},{"id":"finding-KCrbMuGw","date":"2018-10-28T23:50:04.646Z","mediaFilename":"finding-KCrbMuGw.png","caption":"A Mystery – <a href=\"GSFC_20171208_Archive_e001955\">Hubble reveals heart of Lagoon Nebula</a>","altText":"A Mystery @ Hubble reveals heart of Lagoon Nebula! GSFC_20171208_Archive_e001955","postedToGit":true,"htmlFragment":"<li class=\"pane\">\n  <div class=\"time-stamp entry-meta\">\n    <a href=\"finding-KCrbMuGw.html\">\n      <time datetime=\"2018-10-28T23:50:04.646Z\">2018-10-28 19:50:04</time>\n    </a>\n  </div><img src=\"media/finding-KCrbMuGw.png\" alt=\"A Mystery @ Hubble reveals heart of Lagoon Nebula! GSFC_20171208_Archive_e001955\"></video><div class=\"media-caption entry-meta\">A Mystery – <a href=\"GSFC_20171208_Archive_e001955\">Hubble reveals heart of Lagoon Nebula</a></div></li>","postedSingleVideoPage":true},{"id":"finding-balliYOi","date":"2018-10-29T02:50:04.862Z","mediaFilename":"finding-balliYOi.png","caption":"A Mystery ; <a href=\"PIA08262\">The Ring Sculptor</a>!","altText":"A Mystery | The Ring Sculptor PIA08262","postedToGit":true,"htmlFragment":"<li class=\"pane\">\n  <div class=\"time-stamp entry-meta\">\n    <a href=\"finding-balliYOi.html\">\n      <time datetime=\"2018-10-29T02:50:04.862Z\">2018-10-28 22:50:04</time>\n    </a>\n  </div><img src=\"media/finding-balliYOi.png\" alt=\"A Mystery | The Ring Sculptor PIA08262\"></video><div class=\"media-caption entry-meta\">A Mystery ; <a href=\"PIA08262\">The Ring Sculptor</a>!</div></li>","postedSingleVideoPage":true},{"id":"finding-RddECbbH","date":"2018-10-29T05:50:05.890Z","mediaFilename":"finding-RddECbbH.png","caption":"An Unexpected Discovery – <a href=\"PIA01319\">A Star Close Encounter</a>.","altText":"An Unexpected Discovery @ A Star Close Encounter. PIA01319","postedToGit":true,"htmlFragment":"<li class=\"pane\">\n  <div class=\"time-stamp entry-meta\">\n    <a href=\"finding-RddECbbH.html\">\n      <time datetime=\"2018-10-29T05:50:05.890Z\">2018-10-29 01:50:05</time>\n    </a>\n  </div><img src=\"media/finding-RddECbbH.png\" alt=\"An Unexpected Discovery @ A Star Close Encounter. PIA01319\"></video><div class=\"media-caption entry-meta\">An Unexpected Discovery – <a href=\"PIA01319\">A Star Close Encounter</a>.</div></li>","postedSingleVideoPage":true},{"id":"finding-UaFtKleJ","date":"2018-10-29T08:50:06.364Z","mediaFilename":"finding-UaFtKleJ.png","caption":"Something Strange – <a href=\"PIA07225\">New Views of a Familiar Beauty</a>","altText":"Something Strange + New Views of a Familiar Beauty PIA07225","postedToGit":true,"htmlFragment":"<li class=\"pane\">\n  <div class=\"time-stamp entry-meta\">\n    <a href=\"finding-UaFtKleJ.html\">\n      <time datetime=\"2018-10-29T08:50:06.364Z\">2018-10-29 04:50:06</time>\n    </a>\n  </div><img src=\"media/finding-UaFtKleJ.png\" alt=\"Something Strange + New Views of a Familiar Beauty PIA07225\"></video><div class=\"media-caption entry-meta\">Something Strange – <a href=\"PIA07225\">New Views of a Familiar Beauty</a></div></li>","postedSingleVideoPage":true},{"id":"finding-cIRncHTD","date":"2018-10-29T11:50:05.392Z","mediaFilename":"finding-cIRncHTD.png","caption":"Something Strange ; <a href=\"PIA14219\">The Bright Peaks of Mickiewicz</a>","altText":"Something Strange – The Bright Peaks of Mickiewicz! PIA14219","postedToGit":true,"htmlFragment":"<li class=\"pane\">\n  <div class=\"time-stamp entry-meta\">\n    <a href=\"finding-cIRncHTD.html\">\n      <time datetime=\"2018-10-29T11:50:05.392Z\">2018-10-29 07:50:05</time>\n    </a>\n  </div><img src=\"media/finding-cIRncHTD.png\" alt=\"Something Strange – The Bright Peaks of Mickiewicz! PIA14219\"></video><div class=\"media-caption entry-meta\">Something Strange ; <a href=\"PIA14219\">The Bright Peaks of Mickiewicz</a></div></li>","postedSingleVideoPage":true},{"id":"finding-iWvcsIIA","date":"2018-10-29T14:50:06.357Z","mediaFilename":"finding-iWvcsIIA.png","caption":"A Mystery | <a href=\"PIA11457\">F Ring Fender Bender</a>","altText":"A Mystery on F Ring Fender Bender. PIA11457","postedToGit":true,"htmlFragment":"<li class=\"pane\">\n  <div class=\"time-stamp entry-meta\">\n    <a href=\"finding-iWvcsIIA.html\">\n      <time datetime=\"2018-10-29T14:50:06.357Z\">2018-10-29 10:50:06</time>\n    </a>\n  </div><img src=\"media/finding-iWvcsIIA.png\" alt=\"A Mystery on F Ring Fender Bender. PIA11457\"></video><div class=\"media-caption entry-meta\">A Mystery | <a href=\"PIA11457\">F Ring Fender Bender</a></div></li>","postedSingleVideoPage":true},{"id":"finding-pBzptaPp","date":"2018-10-29T17:50:05.995Z","mediaFilename":"finding-pBzptaPp.png","caption":"??? + <a href=\"PIA19937\">Looking over Pluto</a>.","altText":"??? @ Looking over Pluto! PIA19937","postedToGit":true,"htmlFragment":"<li class=\"pane\">\n  <div class=\"time-stamp entry-meta\">\n    <a href=\"finding-pBzptaPp.html\">\n      <time datetime=\"2018-10-29T17:50:05.995Z\">2018-10-29 13:50:05</time>\n    </a>\n  </div><img src=\"media/finding-pBzptaPp.png\" alt=\"??? @ Looking over Pluto! PIA19937\"></video><div class=\"media-caption entry-meta\">??? + <a href=\"PIA19937\">Looking over Pluto</a>.</div></li>","postedSingleVideoPage":true},{"id":"finding-YNYFEIBn","date":"2018-10-29T23:50:05.290Z","mediaFilename":"finding-YNYFEIBn.png","caption":"A Mystery ; <a href=\"PIA11605\">Portrait of Bright Spokes</a>!","altText":"A Mystery ; Portrait of Bright Spokes PIA11605","postedToGit":true,"htmlFragment":"<li class=\"pane\">\n  <div class=\"time-stamp entry-meta\">\n    <a href=\"finding-YNYFEIBn.html\">\n      <time datetime=\"2018-10-29T23:50:05.290Z\">2018-10-29 19:50:05</time>\n    </a>\n  </div><img src=\"media/finding-YNYFEIBn.png\" alt=\"A Mystery ; Portrait of Bright Spokes PIA11605\"></video><div class=\"media-caption entry-meta\">A Mystery ; <a href=\"PIA11605\">Portrait of Bright Spokes</a>!</div></li>","postedSingleVideoPage":true},{"id":"finding-ednbPtGQ","date":"2018-10-30T02:50:06.402Z","mediaFilename":"finding-ednbPtGQ.png","caption":"Something Strange | <a href=\"PIA18668\">Map of Triton</a>.","altText":"Something Strange on Map of Triton. PIA18668","postedToGit":true,"htmlFragment":"<li class=\"pane\">\n  <div class=\"time-stamp entry-meta\">\n    <a href=\"finding-ednbPtGQ.html\">\n      <time datetime=\"2018-10-30T02:50:06.402Z\">2018-10-29 22:50:06</time>\n    </a>\n  </div><img src=\"media/finding-ednbPtGQ.png\" alt=\"Something Strange on Map of Triton. PIA18668\"></video><div class=\"media-caption entry-meta\">Something Strange | <a href=\"PIA18668\">Map of Triton</a>.</div></li>","postedSingleVideoPage":true},{"id":"finding-CZJuUkiR","date":"2018-10-30T05:50:06.703Z","mediaFilename":"finding-CZJuUkiR.png","caption":"Something Strange, Something Strange on <a href=\"PIA13451\">Chasing Chickens in the Lambda Centauri Nebula</a>.","altText":"Something Strange, Something Strange – Chasing Chickens in the Lambda Centauri Nebula PIA13451","postedToGit":true,"htmlFragment":"<li class=\"pane\">\n  <div class=\"time-stamp entry-meta\">\n    <a href=\"finding-CZJuUkiR.html\">\n      <time datetime=\"2018-10-30T05:50:06.703Z\">2018-10-30 01:50:06</time>\n    </a>\n  </div><img src=\"media/finding-CZJuUkiR.png\" alt=\"Something Strange, Something Strange – Chasing Chickens in the Lambda Centauri Nebula PIA13451\"></video><div class=\"media-caption entry-meta\">Something Strange, Something Strange on <a href=\"PIA13451\">Chasing Chickens in the Lambda Centauri Nebula</a>.</div></li>","postedSingleVideoPage":true},{"id":"finding-hCebdBGi","date":"2018-10-30T08:50:05.259Z","mediaFilename":"finding-hCebdBGi.png","caption":"A Mystery – <a href=\"PIA01252\">Mars At Opposition</a>","altText":"A Mystery @ Mars At Opposition. PIA01252","postedToGit":true,"htmlFragment":"<li class=\"pane\">\n  <div class=\"time-stamp entry-meta\">\n    <a href=\"finding-hCebdBGi.html\">\n      <time datetime=\"2018-10-30T08:50:05.259Z\">2018-10-30 04:50:05</time>\n    </a>\n  </div><img src=\"media/finding-hCebdBGi.png\" alt=\"A Mystery @ Mars At Opposition. PIA01252\"></video><div class=\"media-caption entry-meta\">A Mystery – <a href=\"PIA01252\">Mars At Opposition</a></div></li>","postedSingleVideoPage":true},{"id":"finding-dWgMsAMW","date":"2018-10-30T11:50:08.851Z","mediaFilename":"finding-dWgMsAMW.png","caption":"An Unexpected Discovery + <a href=\"PIA06579\">Bright Moon in Darkness</a>.","altText":"An Unexpected Discovery – Bright Moon in Darkness! PIA06579","postedToGit":true,"htmlFragment":"<li class=\"pane\">\n  <div class=\"time-stamp entry-meta\">\n    <a href=\"finding-dWgMsAMW.html\">\n      <time datetime=\"2018-10-30T11:50:08.851Z\">2018-10-30 07:50:08</time>\n    </a>\n  </div><img src=\"media/finding-dWgMsAMW.png\" alt=\"An Unexpected Discovery – Bright Moon in Darkness! PIA06579\"></video><div class=\"media-caption entry-meta\">An Unexpected Discovery + <a href=\"PIA06579\">Bright Moon in Darkness</a>.</div></li>","postedSingleVideoPage":true},{"id":"finding-WFSpsPlO","date":"2018-10-30T14:50:05.918Z","mediaFilename":"finding-WFSpsPlO.png","caption":"An Unexpected Discovery ; <a href=\"PIA15429\">Black Hole Erupts</a>.","altText":"An Unexpected Discovery @ Black Hole Erupts PIA15429","postedToGit":true,"htmlFragment":"<li class=\"pane\">\n  <div class=\"time-stamp entry-meta\">\n    <a href=\"finding-WFSpsPlO.html\">\n      <time datetime=\"2018-10-30T14:50:05.918Z\">2018-10-30 10:50:05</time>\n    </a>\n  </div><img src=\"media/finding-WFSpsPlO.png\" alt=\"An Unexpected Discovery @ Black Hole Erupts PIA15429\"></video><div class=\"media-caption entry-meta\">An Unexpected Discovery ; <a href=\"PIA15429\">Black Hole Erupts</a>.</div></li>","postedSingleVideoPage":true},{"id":"finding-pfnVAvjx","date":"2018-10-30T17:50:06.097Z","mediaFilename":"finding-pfnVAvjx.png","caption":"An Unexpected Discovery @ <a href=\"PIA07981\">Larry Outcrop in False Color</a>.","altText":"An Unexpected Discovery + Larry Outcrop in False Color. PIA07981","postedToGit":true,"htmlFragment":"<li class=\"pane\">\n  <div class=\"time-stamp entry-meta\">\n    <a href=\"finding-pfnVAvjx.html\">\n      <time datetime=\"2018-10-30T17:50:06.097Z\">2018-10-30 13:50:06</time>\n    </a>\n  </div><img src=\"media/finding-pfnVAvjx.png\" alt=\"An Unexpected Discovery + Larry Outcrop in False Color. PIA07981\"></video><div class=\"media-caption entry-meta\">An Unexpected Discovery @ <a href=\"PIA07981\">Larry Outcrop in False Color</a>.</div></li>","postedSingleVideoPage":true},{"id":"finding-IAEXfOBg","date":"2018-10-30T20:50:05.479Z","mediaFilename":"finding-IAEXfOBg.png","caption":"A Mystery ; <a href=\"PIA09293\">Bright Dunes</a>.","altText":"A Mystery ; Bright Dunes! PIA09293","postedToGit":true,"htmlFragment":"<li class=\"pane\">\n  <div class=\"time-stamp entry-meta\">\n    <a href=\"finding-IAEXfOBg.html\">\n      <time datetime=\"2018-10-30T20:50:05.479Z\">2018-10-30 16:50:05</time>\n    </a>\n  </div><img src=\"media/finding-IAEXfOBg.png\" alt=\"A Mystery ; Bright Dunes! PIA09293\"></video><div class=\"media-caption entry-meta\">A Mystery ; <a href=\"PIA09293\">Bright Dunes</a>.</div></li>","postedSingleVideoPage":true},{"id":"finding-bRduknLn","date":"2018-10-30T23:50:04.852Z","mediaFilename":"finding-bRduknLn.png","caption":"An Unexpected Discovery + <a href=\"GSFC_20171208_Archive_e002076\">Hubble Captures Spectacular \"Landscape\" in the Carina Nebula</a>.","altText":"An Unexpected Discovery ; Hubble Captures Spectacular \"Landscape\" in the Carina Nebula. GSFC_20171208_Archive_e002076","postedToGit":true,"htmlFragment":"<li class=\"pane\">\n  <div class=\"time-stamp entry-meta\">\n    <a href=\"finding-bRduknLn.html\">\n      <time datetime=\"2018-10-30T23:50:04.852Z\">2018-10-30 19:50:04</time>\n    </a>\n  </div><img src=\"media/finding-bRduknLn.png\" alt=\"An Unexpected Discovery ; Hubble Captures Spectacular \"Landscape\" in the Carina Nebula. GSFC_20171208_Archive_e002076\"></video><div class=\"media-caption entry-meta\">An Unexpected Discovery + <a href=\"GSFC_20171208_Archive_e002076\">Hubble Captures Spectacular \"Landscape\" in the Carina Nebula</a>.</div></li>","postedSingleVideoPage":true},{"id":"finding-yZBVMqkt","date":"2018-10-31T02:50:06.889Z","mediaFilename":"finding-yZBVMqkt.png","caption":"An Unexpected Discovery, An Unexpected Discovery ; <a href=\"PIA18926\">Planet With Four Stars Artist Concept</a>!","altText":"An Unexpected Discovery, An Unexpected Discovery | Planet With Four Stars Artist Concept. PIA18926","postedToGit":true,"htmlFragment":"<li class=\"pane\">\n  <div class=\"time-stamp entry-meta\">\n    <a href=\"finding-yZBVMqkt.html\">\n      <time datetime=\"2018-10-31T02:50:06.889Z\">2018-10-30 22:50:06</time>\n    </a>\n  </div><img src=\"media/finding-yZBVMqkt.png\" alt=\"An Unexpected Discovery, An Unexpected Discovery | Planet With Four Stars Artist Concept. PIA18926\"></video><div class=\"media-caption entry-meta\">An Unexpected Discovery, An Unexpected Discovery ; <a href=\"PIA18926\">Planet With Four Stars Artist Concept</a>!</div></li>","postedSingleVideoPage":true},{"id":"finding-fNcnGmod","date":"2018-10-31T05:50:06.020Z","mediaFilename":"finding-fNcnGmod.png","caption":"Something Strange + <a href=\"PIA14637\">Another Death Star?</a>.","altText":"Something Strange on Another Death Star?. PIA14637","postedToGit":true,"htmlFragment":"<li class=\"pane\">\n  <div class=\"time-stamp entry-meta\">\n    <a href=\"finding-fNcnGmod.html\">\n      <time datetime=\"2018-10-31T05:50:06.020Z\">2018-10-31 01:50:06</time>\n    </a>\n  </div><img src=\"media/finding-fNcnGmod.png\" alt=\"Something Strange on Another Death Star?. PIA14637\"></video><div class=\"media-caption entry-meta\">Something Strange + <a href=\"PIA14637\">Another Death Star?</a>.</div></li>","postedSingleVideoPage":true}]